rest_framework_jwt_oauth2/__init__.py
rest_framework_jwt_oauth2/app_settings.py
rest_framework_jwt_oauth2/apps.py
rest_framework_jwt_oauth2/middlewares.py
rest_framework_jwt_oauth2/serializers.py
rest_framework_jwt_oauth2/urls.py
rest_framework_jwt_oauth2/views.py
rest_framework_jwt_oauth2/tests/__init__.py
rest_framework_jwt_oauth2/tests/api_fixtures.py
rest_framework_jwt_oauth2/utils/__init__.py
rest_framework_jwt_oauth2/utils/adapter.py
rest_framework_jwt_oauth2/utils/serializers.py
django_rest_framework_jwt_oauth2-0.0.4.dist-info/LICENSE
django_rest_framework_jwt_oauth2-0.0.4.dist-info/METADATA
django_rest_framework_jwt_oauth2-0.0.4.dist-info/WHEEL
django_rest_framework_jwt_oauth2-0.0.4.dist-info/top_level.txt
django_rest_framework_jwt_oauth2-0.0.4.dist-info/RECORD
